image_processing_studies_mvbs/__init__.py
image_processing_studies_mvbs/processing/__init__.py
image_processing_studies_mvbs/processing/combination.py
image_processing_studies_mvbs/processing/transformation.py
image_processing_studies_mvbs/utils/__init__.py
image_processing_studies_mvbs/utils/io.py
image_processing_studies_mvbs/utils/plot.py
image_processing_studies_mvbs-0.0.1.dist-info/METADATA
image_processing_studies_mvbs-0.0.1.dist-info/WHEEL
image_processing_studies_mvbs-0.0.1.dist-info/top_level.txt
image_processing_studies_mvbs-0.0.1.dist-info/RECORD
