Metadata-Version: 2.1
Name: image-processing-studies-mvbs
Version: 0.0.1
Summary: image processing package using skimage to study
Home-page: https://github.com/mvbs3/image-processing-package
Author: Karina, and student Marcelo
Requires-Python: >=3.5
Requires-Dist: matplotlib
Requires-Dist: numpy
Requires-Dist: scikit-image (>=0.16.1)
